NGDataPortal/NGDataPortal.py
NGDataPortal/__init__.py
NGDataPortal/stream_to_resource_id.json
NGDataPortal-1.0.9.dist-info/LICENSE
NGDataPortal-1.0.9.dist-info/METADATA
NGDataPortal-1.0.9.dist-info/WHEEL
NGDataPortal-1.0.9.dist-info/top_level.txt
NGDataPortal-1.0.9.dist-info/RECORD
