Metadata-Version: 2.1
Name: NGDataPortal
Version: 1.0.9
Summary: Package for accessing the NG ESO data portal API
Home-page: https://github.com/AyrtonB/National-Grid-Data-Portal
Author: Ayrton Bourn
Author-email: AyrtonBourn@Outlook.com
License: UNKNOWN
Platform: UNKNOWN
Classifier: Programming Language :: Python :: 3
Classifier: License :: OSI Approved :: MIT License
Classifier: Operating System :: OS Independent
Requires-Python: >=3.6
License-File: LICENSE
